builder.py
ZiPyFilter.cpython-38-x86_64-linux-gnu.so
ZiPyFilter-0.0.1.dist-info/RECORD
ZiPyFilter-0.0.1.dist-info/WHEEL
ZiPyFilter-0.0.1.dist-info/METADATA
ZiPyFilter-0.0.1.dist-info/top_level.txt
ZiPyFilter-0.0.1.dist-info/LICENSE
