Metadata-Version: 2.1
Name: ZiPyFilter
Version: 0.0.1
Summary: Fast Filter for Python 3.6+
Home-page: https://github.com/OmarSiwy/ZiPyFilter
License-File: LICENSE
